odoo/addons/web_view_transition/README.rst
odoo/addons/web_view_transition/__init__.py
odoo/addons/web_view_transition/__manifest__.py
odoo/addons/web_view_transition/i18n/web_view_transition.pot
odoo/addons/web_view_transition/images/config.gif
odoo/addons/web_view_transition/models/__init__.py
odoo/addons/web_view_transition/models/inherited_ir_http.py
odoo/addons/web_view_transition/models/inherited_res_users.py
odoo/addons/web_view_transition/readme/DESCRIPTION.rst
odoo/addons/web_view_transition/readme/USAGE.rst
odoo/addons/web_view_transition/static/description/icon.png
odoo/addons/web_view_transition/static/description/index.html
odoo/addons/web_view_transition/static/src/css/transitions.less
odoo/addons/web_view_transition/static/src/js/view_manager.js
odoo/addons/web_view_transition/view/inherited_view_users_form_simple_modif.xml
odoo/addons/web_view_transition/view/web_view_transition.xml
odoo11_addon_web_view_transition-11.0.1.0.1.dist-info/METADATA
odoo11_addon_web_view_transition-11.0.1.0.1.dist-info/WHEEL
odoo11_addon_web_view_transition-11.0.1.0.1.dist-info/top_level.txt
odoo11_addon_web_view_transition-11.0.1.0.1.dist-info/RECORD
